glslsyntax/__init__.py
glslsyntax/matrices.py
glslsyntax/vectors.py
glslsyntax-1.0.1.dist-info/LICENSE
glslsyntax-1.0.1.dist-info/METADATA
glslsyntax-1.0.1.dist-info/WHEEL
glslsyntax-1.0.1.dist-info/top_level.txt
glslsyntax-1.0.1.dist-info/RECORD
