Metadata-Version: 2.1
Name: glslsyntax
Version: 1.0.1
Summary: Imports GLSL Vector and Matrix notations in python with somme extra features.
Home-page: https://github.com/Neylz/GlslSyntax
Author: Neylz
Author-email: contact@neylz.dev
License: MIT
Project-URL: Bug Tracker, https://github.com/Neylz/GlslSyntax/issues
Keywords: GLSL,VECTORS,VECTOR,MATRIX,MATRICES
Classifier: Programming Language :: Python :: 3
Classifier: License :: OSI Approved :: MIT License
Classifier: Operating System :: OS Independent
Requires-Python: >=3.10
License-File: LICENSE
